nzpython/__init__.py
nzpython/keycloak.py
nzpython/keycloak_test.py
nzpython/spark.py
nzpython-0.1.6.dist-info/METADATA
nzpython-0.1.6.dist-info/WHEEL
nzpython-0.1.6.dist-info/top_level.txt
nzpython-0.1.6.dist-info/RECORD
