Metadata-Version: 2.1
Name: nzpython
Version: 0.1.6
Summary: Python Modules for Nazare
Home-page: https://github.com/ingkle/nzpython
Author: inhyeok.kim
Author-email: inhyeok.kim@ingkle.com
License: UNKNOWN
Platform: UNKNOWN
Requires-Python: >=3.6
